modulo/__init__.py
modulo/modulo.py
modulo-2.0.2.dist-info/LICENSE
modulo-2.0.2.dist-info/METADATA
modulo-2.0.2.dist-info/WHEEL
modulo-2.0.2.dist-info/top_level.txt
modulo-2.0.2.dist-info/RECORD
